svtplay_dl/__init__.py
svtplay_dl/__main__.py
svtplay_dl/error.py
svtplay_dl/log.py
svtplay_dl/output.py
svtplay_dl/fetcher/__init__.py
svtplay_dl/fetcher/dash.py
svtplay_dl/fetcher/hds.py
svtplay_dl/fetcher/hls.py
svtplay_dl/fetcher/http.py
svtplay_dl/fetcher/rtmp.py
svtplay_dl/postprocess/__init__.py
svtplay_dl/service/__init__.py
svtplay_dl/service/aftonbladet.py
svtplay_dl/service/bambuser.py
svtplay_dl/service/bigbrother.py
svtplay_dl/service/cmore.py
svtplay_dl/service/dbtv.py
svtplay_dl/service/disney.py
svtplay_dl/service/dplay.py
svtplay_dl/service/dr.py
svtplay_dl/service/efn.py
svtplay_dl/service/expressen.py
svtplay_dl/service/facebook.py
svtplay_dl/service/filmarkivet.py
svtplay_dl/service/flowonline.py
svtplay_dl/service/hbo.py
svtplay_dl/service/lemonwhale.py
svtplay_dl/service/mtvnn.py
svtplay_dl/service/mtvservices.py
svtplay_dl/service/nhl.py
svtplay_dl/service/nrk.py
svtplay_dl/service/oppetarkiv.py
svtplay_dl/service/picsearch.py
svtplay_dl/service/pokemon.py
svtplay_dl/service/qbrick.py
svtplay_dl/service/radioplay.py
svtplay_dl/service/raw.py
svtplay_dl/service/riksdagen.py
svtplay_dl/service/ruv.py
svtplay_dl/service/solidtango.py
svtplay_dl/service/sr.py
svtplay_dl/service/svt.py
svtplay_dl/service/svtplay.py
svtplay_dl/service/tv4play.py
svtplay_dl/service/twitch.py
svtplay_dl/service/urplay.py
svtplay_dl/service/vg.py
svtplay_dl/service/viaplay.py
svtplay_dl/service/viasatsport.py
svtplay_dl/service/vimeo.py
svtplay_dl/service/youplay.py
svtplay_dl/subtitle/__init__.py
svtplay_dl/utils/__init__.py
svtplay_dl/utils/io.py
svtplay_dl/utils/terminal.py
svtplay_dl/utils/urllib.py
svtplay_dl-1.9.5.data/scripts/svtplay-dl
svtplay_dl-1.9.5.dist-info/DESCRIPTION.rst
svtplay_dl-1.9.5.dist-info/METADATA
svtplay_dl-1.9.5.dist-info/RECORD
svtplay_dl-1.9.5.dist-info/WHEEL
svtplay_dl-1.9.5.dist-info/metadata.json
svtplay_dl-1.9.5.dist-info/top_level.txt
